QingliaoyuSibenTaozhuang/README.md
QingliaoyuSibenTaozhuang/__init__.py
QingliaoyuSibenTaozhuang/__main__.py
QingliaoyuSibenTaozhuang/file.epub
QingliaoyuSibenTaozhuang/index.html
QingliaoyuSibenTaozhuang/css/__init__.py
QingliaoyuSibenTaozhuang/css/annotations.css
QingliaoyuSibenTaozhuang/css/main.css
QingliaoyuSibenTaozhuang/css/normalize.css
QingliaoyuSibenTaozhuang/css/popup.css
QingliaoyuSibenTaozhuang/font/__init__.py
QingliaoyuSibenTaozhuang/font/fontello.eot
QingliaoyuSibenTaozhuang/font/fontello.svg
QingliaoyuSibenTaozhuang/font/fontello.ttf
QingliaoyuSibenTaozhuang/font/fontello.woff
QingliaoyuSibenTaozhuang/img/__init__.py
QingliaoyuSibenTaozhuang/img/annotator-glyph-sprite.png
QingliaoyuSibenTaozhuang/img/annotator-icon-sprite.png
QingliaoyuSibenTaozhuang/img/apple-touch-icon.png
QingliaoyuSibenTaozhuang/img/cancelfullscreen.png
QingliaoyuSibenTaozhuang/img/close.png
QingliaoyuSibenTaozhuang/img/fullscreen.png
QingliaoyuSibenTaozhuang/img/loader.gif
QingliaoyuSibenTaozhuang/img/menu-icon.png
QingliaoyuSibenTaozhuang/img/save.png
QingliaoyuSibenTaozhuang/img/saved.png
QingliaoyuSibenTaozhuang/img/settings-s.png
QingliaoyuSibenTaozhuang/img/settings.png
QingliaoyuSibenTaozhuang/img/star.png
QingliaoyuSibenTaozhuang/js/__init__.py
QingliaoyuSibenTaozhuang/js/epub.js
QingliaoyuSibenTaozhuang/js/epub.min.js
QingliaoyuSibenTaozhuang/js/epub.min.map
QingliaoyuSibenTaozhuang/js/hooks.min.js
QingliaoyuSibenTaozhuang/js/hooks.min.map
QingliaoyuSibenTaozhuang/js/reader.js
QingliaoyuSibenTaozhuang/js/reader.js.map
QingliaoyuSibenTaozhuang/js/reader.min.js
QingliaoyuSibenTaozhuang/js/reader.min.map
QingliaoyuSibenTaozhuang/js/hooks/__init__.py
QingliaoyuSibenTaozhuang/js/hooks/extensions/__init__.py
QingliaoyuSibenTaozhuang/js/hooks/extensions/highlight.js
QingliaoyuSibenTaozhuang/js/libs/__init__.py
QingliaoyuSibenTaozhuang/js/libs/jquery.min.js
QingliaoyuSibenTaozhuang/js/libs/localforage.min.js
QingliaoyuSibenTaozhuang/js/libs/screenfull.js
qingliaoyu_siben_taozhuang-2022.10.3.0.dist-info/METADATA
qingliaoyu_siben_taozhuang-2022.10.3.0.dist-info/WHEEL
qingliaoyu_siben_taozhuang-2022.10.3.0.dist-info/entry_points.txt
qingliaoyu_siben_taozhuang-2022.10.3.0.dist-info/top_level.txt
qingliaoyu_siben_taozhuang-2022.10.3.0.dist-info/RECORD
